snngrow/__init__.py
snngrow/base/__init__.py
snngrow/base/utils.py
snngrow/base/functional/__init__.py
snngrow/base/neuron/BaseNode.py
snngrow/base/neuron/IFNode.py
snngrow/base/neuron/LIFNode.py
snngrow/base/neuron/__init__.py
snngrow/base/surrogate/ATan.py
snngrow/base/surrogate/BaseFunction.py
snngrow/base/surrogate/Sigmoid.py
snngrow/base/surrogate/__init__.py
snngrow/datasets/__init__.py
snngrow-0.1.0.dist-info/LICENSE
snngrow-0.1.0.dist-info/METADATA
snngrow-0.1.0.dist-info/WHEEL
snngrow-0.1.0.dist-info/top_level.txt
snngrow-0.1.0.dist-info/RECORD
